djreport/__init__.py
djreport/admin.py
djreport/apps.py
djreport/conf.py
djreport/mixins.py
djreport/models.py
djreport/serializers.py
djreport/urls.py
djreport/utils.py
djreport/views.py
djreport/engine/__init__.py
djreport/engine/consts.py
djreport/engine/engine.py
djreport/engine/utils.py
djreport/migrations/0001_initial.py
djreport/migrations/__init__.py
djreport-0.1.0.dist-info/LICENSE
djreport-0.1.0.dist-info/METADATA
djreport-0.1.0.dist-info/WHEEL
djreport-0.1.0.dist-info/top_level.txt
djreport-0.1.0.dist-info/RECORD
